{
    "brand":  {
                  "name":  "NorthSpark Studio",
                  "whatsappUrl":  "https://wa.me/972548345192?text=היי%2C%20אשמח%20לדבר%20על%20האתר%20שלי"
              },
    "metadata":  {
                     "title":  "בניית אתרי תדמית לעסקים | NorthSpark Studio",
                     "description":  "אני בונה אתרי תדמית לעסקים, עם תוכן ברור, עיצוב מקצועי ודרך פשוטה ליצור קשר.",
                     "opengraphAlt":  "NorthSpark Studio: בניית אתרי תדמית לעסקים",
                     "opengraphTitleLine1":  "אתר ברור ומקצועי",
                     "opengraphTitleLine2":  "שבאמת מתאים לעסק שלך.",
                     "opengraphFooter":  "קופי · עיצוב · פיתוח"
                 },
    "navigation":  {
                       "items":  [
                                     {
                                         "label":  "שירותים",
                                         "href":  "#services"
                                     },
                                     {
                                         "label":  "עבודות",
                                         "href":  "#work"
                                     },
                                     {
                                         "label":  "תהליך העבודה",
                                         "href":  "#process"
                                     },
                                     {
                                         "label":  "שאלות",
                                         "href":  "#faq"
                                     }
                                 ],
                       "contactLabel":  "דבר איתי"
                   },
    "aria":  {
                 "backToTop":  "NorthSpark Studio, חזרה לראש העמוד",
                 "primaryNavigation":  "ניווט ראשי",
                 "openMenu":  "פתיחת תפריט",
                 "closeMenu":  "סגירת תפריט",
                 "mobileNavigation":  "ניווט למובייל",
                 "footerNavigation":  "ניווט תחתון",
                 "studioServices":  "שירותי NorthSpark Studio",
                 "storyCompass":  "סדר המידע באתר"
             },
    "common":  {
                   "whatsappShort":  "בוא נדבר",
                   "whatsappFull":  "דבר איתי בוואטסאפ",
                   "mobileWhatsapp":  "דבר איתי בוואטסאפ",
                   "watchProcess":  "תהליך העבודה",
                   "watchProject":  "לצפייה בפרויקט"
               },
    "hero":  {
                 "eyebrow":  "בניית אתרי תדמית לעסקים",
                 "title":  {
                               "first":  "אתר שמציג",
                               "second":  "את העסק שלך",
                               "thirdPrefix":  "כמו",
                               "thirdEmphasis":  "שצריך",
                               "thirdSuffix":  "."
                           },
                 "text":  "אני בונה אתרי תדמית לעסקים שמקבלים לקוחות דרך שיחות, הודעות או תורים. יחד נעשה סדר במידע, ואני אבנה ממנו אתר ברור, מקצועי ונוח לשימוש.",
                 "microTrust":  "אפשר להתחיל בהודעה קצרה בוואטסאפ. תספר לי על העסק ואגיד לך בכנות אם אתר הוא הדבר הנכון כרגע.",
                 "services":  [
                                  "הבנת העסק",
                                  "קופי",
                                  "עיצוב",
                                  "פיתוח",
                                  "התאמה למובייל",
                                  "SEO בסיסי"
                              ],
                 "secondaryCta":  {
                                      "desktop":  "תהליך העבודה",
                                      "mobile":  "תהליך העבודה"
                                  }
             },
    "decisionBoard":  {
                          "kicker":  "המידע החשוב באתר",
                          "title":  "לקוחות לא צריכים לחפש לבד את מה שחשוב.",
                          "summary":  "כבר בתחילת האתר צריך להיות ברור מה העסק מציע, למי זה מתאים ולמה כדאי לפנות.",
                          "label":  "קודם עושים סדר בתוכן",
                          "stages":  [
                                         {
                                             "number":  "01",
                                             "title":  "השירות",
                                             "description":  "מה העסק מציע ומה בדיוק מקבלים.",
                                             "tone":  "peach",
                                             "shape":  "circle"
                                         },
                                         {
                                             "number":  "02",
                                             "title":  "התאמה",
                                             "description":  "למי השירות מתאים ובאילו מקרים הוא יכול לעזור.",
                                             "tone":  "olive",
                                             "shape":  "triangle"
                                         },
                                         {
                                             "number":  "03",
                                             "title":  "סיבה לבחור",
                                             "description":  "מה מיוחד בעסק ואילו עבודות או פרטים מחזקים את זה.",
                                             "tone":  "mustard",
                                             "shape":  "square"
                                         },
                                         {
                                             "number":  "04",
                                             "title":  "יצירת קשר",
                                             "description":  "איך מתקשרים, שולחים הודעה או קובעים תור.",
                                             "tone":  "rust",
                                             "shape":  "hexagon"
                                         }
                                     ]
                      },
    "servicesSection":  {
                            "label":  "אתרי תדמית",
                            "title":  "עמוד אחד או אתר עם כמה עמודים?",
                            "intro":  "זה תלוי בכמות השירותים ובתוכן שצריך להציג. אני עוזר לבחור את המבנה הנכון ומטפל בקופי, בעיצוב ובפיתוח עד שהאתר מוכן.",
                            "scopeNote":  "לפני תחילת העבודה אני שולח הצעה מסודרת שמפרטת בדיוק מה כלול.",
                            "aftercareNote":  "אחרי שהאתר עולה אפשר לפנות אליי גם לשינויים קטנים ולתחזוקה.",
                            "helperQuestion":  "לא בטוח איזו אפשרות מתאימה לעסק שלך?",
                            "primaryCta":  "אפשר להתייעץ איתי בוואטסאפ",
                            "items":  [
                                          {
                                              "number":  "01",
                                              "kind":  "brand",
                                              "title":  "אתר תדמית בעמוד אחד | 3,900 ₪",
                                              "text":  "מתאים לעסק שיש לו שירות עיקרי וכמות תוכן לא גדולה. כל המידע החשוב נמצא בעמוד אחד מסודר.",
                                              "tags":  [
                                                           "עמוד אחד מקיף",
                                                           "מבנה וקופי",
                                                           "עיצוב ופיתוח",
                                                           "7 עד 10 ימי עבודה"
                                                       ]
                                          },
                                          {
                                              "number":  "02",
                                              "kind":  "brand",
                                              "title":  "אתר תדמית מלא | 6,900 ₪",
                                              "text":  "מתאים לעסק שיש לו כמה שירותים או הרבה תוכן. כל נושא מקבל מקום משלו, כך שקל יותר להבין ולמצוא את המידע.",
                                              "tags":  [
                                                           "מספר עמודים",
                                                           "עמודים לשירותים שונים",
                                                           "בסיס טוב יותר ל-SEO",
                                                           "15 עד 20 ימי עבודה"
                                                       ]
                                          }
                                      ],
                            "primaryCtaMobile":  "נבדוק התאמה"
                        },
    "work":  {
                 "label":  "עבודות",
                 "title":  "כמה אתרים שבניתי",
                 "text":  "שלושה פרויקטים שונים, שכל אחד מהם נבנה לפי העסק והמידע שהוא צריך להציג.",
                 "ctaText":  "רוצה לדבר על האתר שלך?",
                 "ctaLabel":  "דבר איתי",
                 "projects":  [
                                  {
                                      "name":  "א.ש אינסטלציה",
                                      "text":  "אתר שמרכז את שירותי האינסטלציה והשיקום של העסק ומאפשר לפנות ישירות מהטלפון.",
                                      "outcome":  "המידע מסודר לפי סוגי השירות, כך שלקוחות יכולים למצוא מהר את מה שהם צריכים.",
                                      "tags":  [
                                                   "עסק מקומי",
                                                   "אתר שירות",
                                                   "אמון",
                                                   "יצירת קשר"
                                               ],
                                      "href":  "https://www.as-plumbing-services.com/",
                                      "featured":  true,
                                      "screenshots":  {
                                                          "desktop":  "/projects/as-plumbing-desktop.webp",
                                                          "mobile":  "/projects/as-plumbing-mobile.webp"
                                                      }
                                  },
                                  {
                                      "name":  "Karen Beauty",
                                      "text":  "אתר נקי ועדין שמציג את הטיפולים ואת הסגנון של Karen Beauty.",
                                      "outcome":  "כל טיפול מקבל הסבר קצר, ומשם אפשר לעבור בקלות לקביעת תור.",
                                      "tags":  [
                                                   "יופי וטיפוח",
                                                   "אתר תדמית",
                                                   "עיצוב מותאם"
                                               ],
                                      "href":  "https://karen-beauty.vercel.app/",
                                      "screenshots":  {
                                                          "desktop":  "/projects/karen-beauty-desktop.webp",
                                                          "mobile":  "/projects/karen-beauty-mobile.webp"
                                                      }
                                  },
                                  {
                                      "name":  "נותנים באהבה",
                                      "text":  "עמוד תרומה שמסביר למי תורמים, למה התרומה חשובה ואיך משלימים אותה.",
                                      "outcome":  "כל המידע ותהליך התרומה נמצאים בעמוד אחד.",
                                      "tags":  [
                                                   "עמותה",
                                                   "תרומות",
                                                   "אמון",
                                                   "פעולה"
                                               ],
                                      "href":  "https://donate.notnim.info/",
                                      "screenshots":  {
                                                          "desktop":  "/projects/notnim-beahava-desktop.webp",
                                                          "mobile":  "/projects/notnim-beahava-mobile.webp"
                                                      }
                                  }
                              ]
             },
    "testimonials":  {
                         "_comment":  "יש להוסיף רק המלצה אמיתית בנוסח שאושר לפרסום, יחד עם שם ותפקיד מאושרים. אין להמציא או לשפר טענה באופן שמשנה את משמעותה.",
                         "label":  "המלצות",
                         "title":  "המלצות מלקוחות",
                         "items":  [

                                   ]
                     },
    "process":  {
                    "label":  "תהליך העבודה",
                    "title":  [
                                  "מהשיחה הראשונה",
                                  "עד שהאתר עולה."
                              ],
                    "text":  "התהליך מחולק לארבעה שלבים. בכל שלב ברור על מה עובדים ומה צריך לאשר לפני שממשיכים.",
                    "ctaText":  "רוצה להבין איך התהליך ייראה אצלך?",
                    "ctaLabel":  "נתחיל בשיחה קצרה",
                    "items":  [
                                  {
                                      "number":  "01",
                                      "title":  "שיחת היכרות",
                                      "text":  "אתה מספר לי על העסק, השירותים והלקוחות שאתה רוצה להגיע אליהם.",
                                      "illustration":  "/illustrations/strategy.svg"
                                  },
                                  {
                                      "number":  "02",
                                      "title":  "תוכן",
                                      "text":  "אני מסדר את המידע וכותב את הטקסטים לכל עמוד ולכל חלק באתר.",
                                      "illustration":  "/illustrations/document.svg"
                                  },
                                  {
                                      "number":  "03",
                                      "title":  "עיצוב",
                                      "text":  "אחרי שמאשרים את התוכן, אני מעצב את האתר לפי הסגנון של העסק.",
                                      "illustration":  "/illustrations/trust.svg"
                                  },
                                  {
                                      "number":  "04",
                                      "title":  "בנייה והשקה",
                                      "text":  "אני בונה את האתר, מתאים אותו למובייל ובודק שהכול עובד לפני שהוא עולה לאוויר.",
                                      "illustration":  "/illustrations/browser.svg"
                                  }
                              ],
                    "ctaLabelMobile":  "נדבר על האתר"
                },
    "about":  {
                  "expertise":  "קופי · עיצוב · פיתוח",
                  "label":  "נעים להכיר",
                  "title":  "אני פיני, האדם שמאחורי NorthSpark.",
                  "paragraphs":  [
                                     "אני עובד על כל אתר בעצמי, מהשיחה הראשונה ועד שהוא עולה לאוויר.",
                                     "לאורך כל הפרויקט אתה מדבר איתי ישירות. אין העברות בין אנשי צוות ואין צורך להסביר את העסק מחדש בכל שלב."
                                 ],
                  "ctaLabel":  "ספר לי על העסק ועל האתר שאתה צריך",
                  "strengths":  [
                                    {
                                        "title":  "עבודה ישירה מולי",
                                        "text":  "אותו אדם לאורך כל הפרויקט"
                                    },
                                    {
                                        "title":  "כתיבה בגובה העיניים",
                                        "text":  "בלי מילים שלקוחות לא משתמשים בהן"
                                    },
                                    {
                                        "title":  "עיצוב שמתאים לעסק",
                                        "text":  "לא תבנית שמחליפים בה צבעים"
                                    },
                                    {
                                        "title":  "אתר מוכן לשימוש",
                                        "text":  "כולל מובייל ובדיקות לפני ההשקה"
                                    }
                                ],
                  "ctaLabelMobile":  "ספר לי על האתר"
              },
    "faq":  {
                "label":  "שאלות נפוצות",
                "title":  "מה כדאי לדעת לפני שמתחילים",
                "text":  "אלה הדברים שבדרך כלל רוצים לדעת לפני שמחליטים להתחיל.",
                "contactText":  "נשארה לך שאלה?",
                "contactLabel":  "שלח לי הודעה בוואטסאפ",
                "items":  [
                              {
                                  "question":  "כמה זמן לוקח לבנות אתר?",
                                  "answer":  "אתר בעמוד אחד מוכן בדרך כלל בתוך 7 עד 10 ימי עבודה. אתר מלא מוכן בדרך כלל בתוך 15 עד 20 ימי עבודה. הזמן נספר אחרי התשלום הראשון וקבלת החומרים, ולא כולל ימים שבהם מחכים למשוב או לאישור."
                              },
                              {
                                  "question":  "כמה עולה לבנות אתר?",
                                  "answer":  "אתר בעמוד אחד עולה 3,900 ₪. אתר מלא עולה 6,900 ₪. לפני שמתחילים אני שולח הצעה שמפרטת בדיוק מה כלול. NorthSpark הוא עוסק פטור, ולכן לא מתווסף מע״מ."
                              },
                              {
                                  "question":  "מה כולל השירות?",
                                  "answer":  "השירות כולל הבנת העסק, סידור התוכן, כתיבת הטקסטים, עיצוב, פיתוח, התאמה למובייל, SEO בסיסי ובדיקות לפני ההשקה. ההיקף המדויק מופיע בהצעה."
                              },
                              {
                                  "question":  "האם צריך להגיע עם טקסטים מוכנים?",
                                  "answer":  "לא. אם יש לך טקסטים או חומרים קיימים, נשתמש בהם כבסיס. אני מסדר את המידע וכותב את הטקסטים לאתר, ואתה עובר עליהם ומאשר שהכול מדויק."
                              },
                              {
                                  "question":  "האם האתר כולל SEO?",
                                  "answer":  "כן. כל אתר כולל SEO בסיסי לפי ההיקף שסוכם. אני מסדר את הכותרות, התיאורים, הכתובות והקישורים, ומחבר כלי מדידה כשיש גישה אליהם. אי אפשר להבטיח מקום מסוים בתוצאות החיפוש."
                              },
                              {
                                  "question":  "למי השירות מתאים ולמי פחות?",
                                  "answer":  "השירות מתאים לעסק שרוצה אתר תדמית מקצועי ומוכן להשקיע בתוכן ובעיצוב. הוא פחות מתאים למי שמחפש את האפשרות הזולה ביותר, צריך חנות אונליין או מצפה להבטחה ללידים ולמקום בגוגל."
                              }
                          ],
                "contactLabelMobile":  "שלח לי הודעה"
            },
    "finalCta":  {
                     "title":  "צריך אתר חדש לעסק?",
                     "text":  "שלח לי הודעה קצרה וספר לי על העסק. אשאל כמה שאלות ואגיד לך איזו אפשרות מתאימה, ואם בכלל נכון להתחיל מאתר.",
                     "secondaryCta":  "רוצה לראות עבודות?"
                 },
    "footer":  {
                   "tagline":  "אתרי תדמית לעסקים.",
                   "copyright":  "© 2026 NorthSpark Studio. כל הזכויות שמורות.",
                   "credit":  "קופי, עיצוב ופיתוח על ידי NorthSpark Studio.",
                   "links":  [
                                 {
                                     "label":  "שירותים",
                                     "href":  "#services"
                                 },
                                 {
                                     "label":  "תהליך העבודה",
                                     "href":  "#process"
                                 },
                                 {
                                     "label":  "עבודות",
                                     "href":  "#work"
                                 },
                                 {
                                     "label":  "שאלות",
                                     "href":  "#faq"
                                 },
                                 {
                                     "label":  "דבר איתי",
                                     "href":  "#contact"
                                 }
                             ]
               }
}
