{
  "brand": {
    "name": "Velora Studio",
    "whatsappUrl": "https://wa.me/972548345192?text=היי%2C%20אשמח%20לדבר%20על%20האתר%20שלי"
  },
  "metadata": {
    "title": "Velora Studio – סטודיו לבניית אתרים | אתרי תדמית, דפי נחיתה ו-eCommerce",
    "description": "סטודיו לבניית אתרים שמשלב אסטרטגיה, קופי, עיצוב ופיתוח. בונים אתרי תדמית, דפי נחיתה וחנויות אונליין שמביאים פניות. דברו איתנו בוואטסאפ.",
    "opengraphAlt": "Velora Studio — אתרים שנבנים סביב הסיבה שהלקוח צריך לבחור בך",
    "opengraphTitleLine1": "לא מתחילים מתבנית.",
    "opengraphTitleLine2": "מתחילים מהסיבה שהלקוח צריך לבחור בך.",
    "opengraphFooter": "Strategy · Copy · Design · Development · Motion"
  },
  "navigation": {
    "items": [
      {
        "label": "שירותים",
        "href": "#services"
      },
      {
        "label": "עבודות",
        "href": "#work"
      },
      {
        "label": "תהליך",
        "href": "#process"
      },
      {
        "label": "שאלות",
        "href": "#faq"
      }
    ],
    "contactLabel": "צור קשר"
  },
  "aria": {
    "backToTop": "Velora Studio — חזרה לראש העמוד",
    "primaryNavigation": "ניווט ראשי",
    "openMenu": "פתיחת תפריט",
    "closeMenu": "סגירת תפריט",
    "mobileNavigation": "ניווט למובייל",
    "footerNavigation": "ניווט תחתון",
    "studioServices": "שירותי הסטודיו",
    "storyCompass": "Story Compass"
  },
  "common": {
    "whatsappShort": "בוא נדבר",
    "whatsappFull": "דבר איתנו בוואטסאפ",
    "mobileWhatsapp": "דבר איתנו בוואטסאפ",
    "watchProcess": "צפה איך התהליך עובד",
    "watchProject": "צפה בפרויקט"
  },
  "hero": {
    "eyebrow": "סטודיו לאתרים שמובילים להחלטה",
    "title": {
      "first": "לא מתחילים מתבנית.",
      "second": "מתחילים מהסיבה",
      "thirdPrefix": "שהלקוח צריך",
      "thirdEmphasis": "לבחור בך",
      "thirdSuffix": "."
    },
    "text": "ב-Velora Studio אנחנו בונים אתרי תדמית, דפי נחיתה וחוויות דיגיטליות עם אסטרטגיה, קופי, עיצוב ופיתוח תחת קורת גג אחת. כך האתר שלך לא רק נראה טוב, הוא גם מביא פניות.",
    "microTrust": "בלי טפסים ארוכים ובלי התחייבות. שיחת וואטסאפ קצרה — ותוך כמה דקות נבין יחד אם ומה נכון לבנות.",
    "services": [
      "אתרי תדמית",
      "דפי נחיתה",
      "eCommerce",
      "Story Scrolling",
      "אוטומציות",
      "עיצוב מוצר"
    ]
  },
  "decisionBoard": {
    "kicker": "למה אתרים נכשלים",
    "title": "אתר לא נכשל בגלל עיצוב. הוא נכשל כשהלקוח לא מצליח להחליט.",
    "summary": "כדי שאתר יוביל לפנייה, הוא צריך לענות מהר על ארבעה דברים: מסר, אמון, הוכחה ופעולה.",
    "label": "אסטרטגיה לפני עיצוב",
    "stages": [
      {
        "number": "01",
        "title": "מסר",
        "description": "הלקוח שנוחת באתר שלך מבין תוך חמש שניות למה לבחור דווקא בך — לא רק מה אתה מוכר.",
        "tone": "peach",
        "shape": "circle"
      },
      {
        "number": "02",
        "title": "אמון",
        "description": "כל עמוד, כל כפתור וכל משפט עובדים יחד — כדי שהלקוח ירגיש שהוא במקום הנכון, לא רק שהאתר יפה.",
        "tone": "olive",
        "shape": "triangle"
      },
      {
        "number": "03",
        "title": "הוכחה",
        "description": "מוכיחים את ההבטחה עם דוגמאות אמיתיות מהשטח, לא רק הצהרות.",
        "tone": "mustard",
        "shape": "square"
      },
      {
        "number": "04",
        "title": "פעולה",
        "description": "מובילים את הלקוח לצעד הבא, בבירור ובלי מאמץ.",
        "tone": "rust",
        "shape": "hexagon"
      }
    ]
  },
  "servicesSection": {
    "label": "השירותים שלנו",
    "title": "אתרים שמבוססים על מטרה ברורה",
    "intro": "כל עסק הוא עולם בפני עצמו. לכן אנחנו לא בונים אתר לפי תבנית, אלא לפי המטרה שלך, הקהל שלך ולאן אתה רוצה להגיע.",
    "note": "ארבע משפחות של אתרים, כל אחת נבנית סביב מטרה עסקית אחרת.",
    "audienceNote": "מתאים לך בין אם אתה מתחיל מאפס בלי אתר בכלל, ובין אם יש לך כבר אתר או מותג שדורש רענון.",
    "helperQuestion": "איזה סוג אתר מתאים לעסק שלך?",
    "primaryCta": "בואו נבין יחד בוואטסאפ",
    "items": [
      {
        "number": "01",
        "kind": "landing",
        "title": "דפי נחיתה",
        "text": "דף אחד, מטרה אחת. בנוי להניע לפעולה מהירה וברורה — השארת פרטים, רכישה או קביעת פגישה.",
        "tags": [
          "Leads",
          "Conversion",
          "Focus"
        ]
      },
      {
        "number": "02",
        "kind": "brand",
        "title": "אתרי תדמית פרימיום",
        "text": "אתר תדמית שבונה אמון, מסביר את הערך שלך ומציג את העסק שלך בצורה שמשקפת אותו נאמנה.",
        "tags": [
          "Brand",
          "Trust",
          "Professional"
        ]
      },
      {
        "number": "03",
        "kind": "story",
        "title": "Story Scrolling",
        "text": "טכניקת גלילה שהופכת מסר מורכב לחוויה מדורגת וברורה. מתאים למותגים ולפרויקטים שרוצים להשאיר רושם עמוק.",
        "tags": [
          "Story",
          "Engagement",
          "Emotion"
        ]
      },
      {
        "number": "04",
        "kind": "commerce",
        "title": "חוויות eCommerce",
        "text": "חנות אונליין חכמה, ממוקדת וקלה לתפעול — שמביאה לקוחות לקנות ולחזור שוב.",
        "tags": [
          "Shop",
          "UX",
          "Conversion"
        ]
      }
    ]
  },
  "storyScrolling": {
    "label": "Story Scrolling",
    "title": "כשהמסר מורכב, הגלילה הופכת אותו לסיפור.",
    "text": "Story Scrolling מאפשר להוביל את הלקוח דרך רעיון, מוצר או תהליך בצורה הדרגתית. במקום להעמיס את כל המידע בבת אחת, האתר בונה הבנה שלב אחרי שלב.",
    "compassBefore": "מעוד עמוד יפה",
    "compassAfter": "למסלול החלטה ברור.",
    "ctaText": "רוצה אתר שמספר את הסיפור שלך נכון?",
    "ctaLabel": "בוא נדבר על הסיפור שלך",
    "cards": [
      {
        "illustration": "/illustrations/browser.svg",
        "lines": [
          "הלקוח נכנס לאתר.",
          "הוא לא מחפש עיצוב."
        ],
        "strong": "הוא מחפש תשובה מהירה."
      },
      {
        "illustration": "/illustrations/message.svg",
        "lines": [
          "אם המסר מטושטש,"
        ],
        "strong": "שום עיצוב לא יציל את ההחלטה."
      },
      {
        "illustration": "/illustrations/strategy.svg",
        "intro": "אתר נכון מוביל את הלקוח:",
        "path": [
          "מהבנה",
          "לביטחון",
          "להוכחה",
          "לפעולה"
        ]
      },
      {
        "illustration": "/illustrations/trust.svg",
        "intro": "בסוף, האתר צריך לעשות דבר אחד:",
        "strong": "להפוך עניין לפנייה."
      }
    ]
  },
  "work": {
    "label": "עבודות",
    "title": "עבודות שמראות חשיבה, לא רק עיצוב.",
    "text": "כל פרויקט נבנה סביב מטרה אחרת: להסביר מוצר, לבנות ביטחון, להוביל לפנייה או להציג מותג בדיוק כמו שהוא.",
    "ctaText": "רוצה גם אתר שירגיש ככה?",
    "ctaLabel": "בוא נדבר",
    "projects": [
      {
        "name": "א.ש אינסטלציה",
        "text": "אתר לעסק שירות מקומי, שנועד ליצור ביטחון מהיר, להסביר את השירותים ולהוביל לקוחות לפנייה ישירה.",
        "outcome": "מטרת האתר: להוביל לפנייה טלפונית מהירה מלקוחות באזור.",
        "tags": [
          "Local Business",
          "Service Website",
          "Trust",
          "Leads"
        ],
        "href": "https://as-plumbing-cyan.vercel.app/",
        "featured": true,
        "screenshots": {
          "desktop": "/projects/as-plumbing-desktop.webp",
          "mobile": "/projects/as-plumbing-mobile.webp"
        }
      },
      {
        "name": "Karen Beauty",
        "text": "אתר למותג יופי, עם שפה נקייה ועדינה שמטרתה לשדר מקצועיות, אסתטיקה ומהימנות.",
        "outcome": "מטרת האתר: לשדר מקצועיות ואמון שמובילים לקביעת תור.",
        "tags": [
          "Beauty",
          "Premium",
          "Brand Website"
        ],
        "href": "https://karen-beauty.vercel.app/",
        "screenshots": {
          "desktop": "/projects/karen-beauty-desktop.webp",
          "mobile": "/projects/karen-beauty-mobile.webp"
        }
      },
      {
        "name": "נותנים באהבה",
        "text": "אתר תרומות שמציג מטרה חברתית בצורה ברורה, בונה אמון ומוביל את המשתמש לפעולת תרומה.",
        "outcome": "מטרת האתר: להוביל לפעולת תרומה בביטחון מלא.",
        "tags": [
          "Donation",
          "Nonprofit",
          "Trust",
          "CTA"
        ],
        "href": "https://donate.notnim.info/",
        "screenshots": {
          "desktop": "/projects/notnim-beahava-desktop.webp",
          "mobile": "/projects/notnim-beahava-mobile.webp"
        }
      }
    ]
  },
  "testimonials": {
    "_comment": "יש להדביק כאן את הציטוט המדויק מבעל עמותת 'נותנים באהבה', עם שמו ותפקידו, רק לאחר אישור מפורש שלו לפרסום. לא להמציא ניסוח — רק להעתיק את מה שנאמר בפועל, ואפשר לערוך קלות לשפה כתובה בלי לשנות משמעות.",
    "label": "לקוחות מספרים",
    "title": "לא רק אנחנו חושבים ככה.",
    "items": [
      {
        "quote": "[להדביק כאן את הציטוט המקורי מבעל העמותה]",
        "name": "[שם בעל העמותה, לפי אישורו לפרסום]",
        "role": "בעל עמותת נותנים באהבה"
      }
    ]
  },
  "process": {
    "label": "תהליך",
    "title": [
      "תהליך ברור. אתר מדויק.",
      "בלי לנחש בדרך."
    ],
    "text": "כדי שאתר יעבוד נכון, צריך לבנות אותו בסדר הנכון: להבין את העסק, לדייק את המסר, לתכנן את המבנה, ורק אחר כך לגשת לעיצוב ופיתוח.",
    "ctaText": "רוצה להבין איך זה ייראה אצלך?",
    "ctaLabel": "נתחיל באפיון קצר",
    "items": [
      {
        "number": "01",
        "title": "אפיון והבנה",
        "text": "מבינים מה העסק מוכר, מי הלקוח הנכון, מה מפריע לו לבחור בך, ומה האתר צריך להבהיר לו.",
        "illustration": "/illustrations/strategy.svg"
      },
      {
        "number": "02",
        "title": "מסר ומבנה",
        "text": "מגדירים את הסיפור של האתר: מה מופיע ראשון, איך נבנה הביטחון, ואיפה הלקוח מקבל את הסיבה לפנות.",
        "illustration": "/illustrations/document.svg"
      },
      {
        "number": "03",
        "title": "עיצוב וחוויה",
        "text": "יוצרים עיצוב נקי וברמה גבוהה, שמחזק את המסר ולא מתחרה בו.",
        "illustration": "/illustrations/trust.svg"
      },
      {
        "number": "04",
        "title": "פיתוח והשקה",
        "text": "בונים אתר מהיר ורספונסיבי, מותאם למובייל, עם קריאות לפעולה ברורות וחיבורים בסיסיים לפי הצורך.",
        "illustration": "/illustrations/browser.svg"
      }
    ]
  },
  "about": {
    "expertise": "אסטרטגיה · קופי · עיצוב · פיתוח",
    "label": "על הסטודיו",
    "title": "מאחורי Velora Studio עומדת חשיבה שמחברת בין עסק, מסר וטכנולוגיה.",
    "paragraphs": [
      "Velora Studio הוקם מתוך הבנה שאתר טוב לא מתחיל בעיצוב, אלא בשאלה עמוקה יותר: למה שהלקוח יבחר דווקא בעסק הזה?",
      "אנחנו משלבים חשיבה עסקית, כתיבה שיווקית, עיצוב נקי ופיתוח מודרני, כדי לבנות אתרים שמרגישים ממוקדים, נראים ברמה גבוהה ומובילים את המשתמש לפעולה ברורה."
    ],
    "ctaLabel": "ספר לנו על האתר שאתה רוצה לבנות",
    "strengths": [
      {
        "title": "חשיבה עסקית",
        "text": "לפני עיצוב"
      },
      {
        "title": "קופי ומבנה",
        "text": "שמובילים להחלטה"
      },
      {
        "title": "עיצוב ברמה גבוהה",
        "text": "נקי ולא גנרי"
      },
      {
        "title": "פיתוח מודרני",
        "text": "מהיר ורספונסיבי"
      }
    ]
  },
  "faq": {
    "label": "שאלות נפוצות",
    "title": "שאלות שעולות לפני שמתחילים.",
    "text": "לפני שבונים אתר, טבעי לרצות להבין איך נראה התהליך, מה כלול, עד כמה עמוק נכנסים לאסטרטגיה והאם זה בכלל מתאים לעסק שלך.",
    "contactText": "יש לך שאלה אחרת?",
    "contactLabel": "שלח הודעה בוואטסאפ",
    "items": [
      {
        "question": "כמה זמן לוקח לבנות אתר?",
        "answer": "זה תלוי בסוג האתר, כמות העמודים, היקף הקופי, והאם נדרשות אנימציות או חוויות מיוחדות. דף נחיתה יכול להיות מהיר יחסית, בעוד שאתר תדמית מלא דורש יותר אפיון, כתיבה, עיצוב ופיתוח."
      },
      {
        "question": "האם אתם רק מעצבים או גם מפתחים את האתר?",
        "answer": "אנחנו ב-Velora Studio מטפלים בכל המעטפת: בחשיבה, במבנה, בקופי, בעיצוב ובפיתוח. המטרה היא לא להעביר קובץ עיצוב, אלא לבנות אתר שלם שעובד נכון."
      },
      {
        "question": "האם צריך להגיע עם טקסטים מוכנים?",
        "answer": "לא בהכרח. אם יש לך חומרים קיימים, נשתמש בהם כבסיס. אם אין, נבנה יחד את המסרים המרכזיים ונכתוב את התוכן לפי המבנה הנכון לאתר."
      },
      {
        "question": "האם האתר יהיה מותאם למובייל?",
        "answer": "בוודאי. אנחנו מתכננים את האתר מראש גם לדסקטופ וגם למובייל, כדי שהחוויה, הקריאה לפעולה והמסר יעבדו נכון בכל גודל מסך."
      },
      {
        "question": "האם אפשר לבנות אתר פשוט בלי אנימציות מיוחדות?",
        "answer": "כן. Motion ו-Story Scrolling נכנסים לתמונה רק אם הם משרתים את המסר. אם אתר נקי, חד ומהיר יעשה את העבודה טוב יותר, זה הכיוון שניקח."
      },
      {
        "question": "מה זה Story Scrolling?",
        "answer": "Story Scrolling הוא שימוש מכוון בגלילה: כל מסך חושף עוד שכבה, עד שהלקוח מגיע להבנה מלאה בלי שהרגיש שהוצף במידע."
      },
      {
        "question": "האם אתם בונים גם חנויות אונליין (eCommerce)?",
        "answer": "כן. אנחנו בונים חנויות אונליין ממוקדות וקלות לתפעול, מהתשתית ועד לעיצוב, כך שהלקוחות שלך יוכלו לקנות בקלות ולחזור שוב."
      },
      {
        "question": "האם אפשר לשדרג אתר קיים ולא לבנות מאפס?",
        "answer": "כן. אם יש אתר קיים עם בסיס טוב, בודקים מה לא עובד במסר, במבנה, בעיצוב או בקריאות לפעולה, ובונים תוכנית שיפור ממוקדת. אם הבסיס חלש מדי, לרוב עדיף לבנות מחדש בצורה נכונה."
      },
      {
        "question": "כמה עולה לבנות אתר?",
        "answer": "המחיר תלוי בסוג האתר, כמות העבודה, עומק האפיון, ורמת העיצוב והפיתוח הנדרשים. אחרי שיחת אפיון קצרה אפשר להבין מה נכון לבנות ומה סדר הגודל."
      },
      {
        "question": "למי השירות פחות מתאים?",
        "answer": "מי שמחפש בעיקר את הפתרון הזול והמהיר ביותר שיש, כנראה ימצא אצל ספקים אחרים התאמה טובה יותר. השירות בנוי למי שרוצה אתר מדויק ומקצועי, שמושקעת בו חשיבה אסטרטגית ושמטרתו להניב תוצאה עסקית."
      }
    ]
  },
  "finalCta": {
    "title": "אם האתר שלך לא מסביר למה לבחור בך, זה המקום להתחיל.",
    "text": "בשיחת אפיון קצרה בוואטסאפ נבין מה העסק שלך צריך לשדר, מה הלקוח צריך להבין, ואיזה אתר נכון לבנות כדי להוביל אותו לפעולה. בלי טפסים ארוכים ובלי התחייבות — ותוך כמה דקות נדע יחד אם ומה נכון לבנות.",
    "secondaryCta": "רוצה לראות דוגמאות?"
  },
  "footer": {
    "tagline": "אתרים שנבנים סביב הסיבה שהלקוח צריך לבחור בך.",
    "copyright": "© 2026 Velora Studio. כל הזכויות שמורות.",
    "credit": "Strategy, copy, design, development and motion.",
    "links": [
      {
        "label": "שירותים",
        "href": "#services"
      },
      {
        "label": "תהליך",
        "href": "#process"
      },
      {
        "label": "עבודות",
        "href": "#work"
      },
      {
        "label": "שאלות",
        "href": "#faq"
      },
      {
        "label": "צור קשר",
        "href": "#contact"
      }
    ]
  }
}